{
      "Titular": "(Brico Depot) Euro Depot España, SA",
      "Contrato": "AA2400305",
      "Lugar de recogida": "(Brico Depot) Euro Depot España, SA, Brico Depot Palma",
      "Lineas del DU": [
            {
                  "Producto": "[TC] CAMBIO",
                  "Unidades": 1,
                  "Envase": "[EC] CONTENEDOR C (28 m3)",
                  "Residuo": null,
                  "product_id": 2603,
                  "container_id": 2681,
                  "waste_id": 2607
            },
            {
                  "Producto": "[RVOLIOC] RESIDUOS BANALES (INDUSTRIAL O COMERCIAL)",
                  "Unidades": 1,
                  "Envase": "[EC] CONTENEDOR C (28 m3)",
                  "Residuo": null,
                  "product_id": 2607,
                  "container_id": 2681,
                  "waste_id": null
            }
      ],
      "Categoria de vehiculo": "Contenedores/Ganchos",
      "holder_id": 27721,
      "agreement_id": 832,
      "pickup_id": 30259,
      "category_fleet_id": 6,
      "Track_Gmail_Uid": "1933f29ebecf0823"
}