{
      "Titular": "Werkhaus SL",
      "Contrato": "AA2300079",
      "Lugar de recogida": "Werkhaus SL, Bauhaus Mallorca",
      "Categoria de vehiculo": "RPs",
      "Lineas del DU": [
            {
                  "Producto": "[TT] TRANSPORTE",
                  "Unidades": 1,
                  "Envase": null,
                  "Residuo": null,
                  "product_id": 2601,
                  "container_id": null,
                  "waste_id": null
            },
            {
                  "Producto": "[RFR5SPP] RAEE FR5 PEQUEÑOS CON S.P. PROFESIONAL",
                  "Unidades": 3,
                  "Envase": "[EBBH1M3] BIG BAG HOMOLOGADO RP 1 m3",
                  "Residuo": null,
                  "product_id": 2591,
                  "container_id": 2707,
                  "waste_id": null
            },
            {
                  "Producto": "[EBBH1M3] BIG BAG HOMOLOGADO RP 1 m3",
                  "Unidades": 3,
                  "Envase": null,
                  "Residuo": null,
                  "product_id": 2707,
                  "container_id": null,
                  "waste_id": null
            }
      ],
      "holder_id": 28274,
      "agreement_id": 14,
      "pickup_id": 30812,
      "category_fleet_id": 7,
      "Track_Gmail_Uid": "192adabf7b7fbb49"
}